positivenegative_library-0.1.1.dist-info/licenses/LICENSE
positvenegative/__init__.py
positvenegative/__main__.py
positvenegative/core.py
positivenegative_library-0.1.1.dist-info/METADATA
positivenegative_library-0.1.1.dist-info/WHEEL
positivenegative_library-0.1.1.dist-info/entry_points.txt
positivenegative_library-0.1.1.dist-info/top_level.txt
positivenegative_library-0.1.1.dist-info/RECORD
