Metadata-Version: 2.4
Name: PositiveNegative-Library
Version: 0.1.1
Summary: Check if a number is positive, negative, or zero
Author: Rahaf Salh Qadah
Author-email: Rahaf Salh Qadah <Rahafsalhqadah2@gmail.com>
License: 
Requires-Python: >=3.7
License-File: LICENSE
Dynamic: author
Dynamic: license-file
Dynamic: requires-python
